Whittler/Whittler.py
Whittler/__init__.py
Whittler/__main__.py
Whittler/config.py
Whittler/classes/CommandBase.py
Whittler/classes/CommandDatabase.py
Whittler/classes/MemoryCompressor.py
Whittler/classes/Metadata.py
Whittler/classes/NestedObjectPointer.py
Whittler/classes/RelevanceFilteredResultList.py
Whittler/classes/RelevanceInterface.py
Whittler/classes/Result.py
Whittler/classes/ResultDatabase.py
Whittler/classes/ResultDictContainer.py
Whittler/classes/Singleton.py
Whittler/classes/__init__.py
Whittler/classes/input_utils.py
Whittler/modules/__init__.py
Whittler/modules/_sample_module.py
Whittler/modules/bandit.py
Whittler/modules/brakeman.py
Whittler/modules/devskim.py
Whittler/modules/gosec.py
Whittler/modules/plaintext.py
Whittler/modules/pssa_csv.py
Whittler/modules/sarif.py
Whittler/modules/semgrep.py
Whittler/modules/trivy-conf.py
Whittler/modules/trivy-vulns.py
Whittler/modules/trufflehog.py
carver-1.3.1.data/scripts/Whittler.py
carver-1.3.1.dist-info/LICENSE
carver-1.3.1.dist-info/METADATA
carver-1.3.1.dist-info/WHEEL
carver-1.3.1.dist-info/top_level.txt
carver-1.3.1.dist-info/RECORD
