Metadata-Version: 2.1
Name: carver
Version: 1.3.1
Summary: A machine-learning-capable modular shell for reducing large datasets (especially code static analysis tool outputs)
Home-page: https://github.com/BenEgeIzmirli/Whittler
Download-URL: https://github.com/BenEgeIzmirli/Whittler/archive/1.3.1.tar.gz
Author: Ben Ege Izmirli
Author-email: benegegalaxy@gmail.com
License: MIT
Platform: UNKNOWN
Classifier: Programming Language :: Python :: 3
Classifier: License :: OSI Approved :: MIT License
Classifier: Operating System :: OS Independent
Classifier: Environment :: Console
Classifier: Intended Audience :: Developers
Classifier: Intended Audience :: Information Technology
Classifier: Topic :: Security
Classifier: Topic :: Database
Classifier: Topic :: Utilities
Classifier: Topic :: Text Processing :: Linguistic
License-File: LICENSE
Requires-Dist: numpy
